MANIFEST.in
README.md
setup.py
latexifier/__init__.py
latexifier/latexifier.py
latexifier.egg-info/PKG-INFO
latexifier.egg-info/SOURCES.txt
latexifier.egg-info/dependency_links.txt
latexifier.egg-info/requires.txt
latexifier.egg-info/top_level.txt