Metadata-Version: 2.1
Name: latexifier
Version: 1.0.8
Summary: A package to convert python objects into latex strings
Home-page: https://github.com/Guillaume-Garrigos/latexify
Author: Guillaume Garrigos
Author-email: guillaume.garrigos@lpsm.paris
License: MIT
Platform: UNKNOWN
Classifier: Programming Language :: Python :: 3
Classifier: License :: OSI Approved :: MIT License
Classifier: Operating System :: OS Independent
Requires-Python: >=3.7
